genome_to_sqlite/__init__.py
genome_to_sqlite/cli.py
genome_to_sqlite/utils.py
genome_to_sqlite-0.1.dist-info/LICENSE
genome_to_sqlite-0.1.dist-info/METADATA
genome_to_sqlite-0.1.dist-info/WHEEL
genome_to_sqlite-0.1.dist-info/entry_points.txt
genome_to_sqlite-0.1.dist-info/top_level.txt
genome_to_sqlite-0.1.dist-info/RECORD
