Metadata-Version: 2.1
Name: genome-to-sqlite
Version: 0.1
Summary: Import your genome into a SQLite database
Home-page: https://github.com/dogsheep/genome-to-sqlite
Author: Simon Willison
License: Apache License, Version 2.0
Platform: UNKNOWN
Requires-Dist: sqlite-utils
Provides-Extra: test
Requires-Dist: pytest ; extra == 'test'
